data/PVS6 Access and API.pdf
data/pvs6-swagger.json
doc/source/conf.py
sungazer/__init__.py
sungazer/client.py
sungazer/py.typed
sungazer/cli/__init__.py
sungazer/cli/device.py
sungazer/cli/firmware.py
sungazer/cli/grid_profile.py
sungazer/cli/main.py
sungazer/cli/network.py
sungazer/cli/session.py
sungazer/models/__init__.py
sungazer/models/devices.py
sungazer/models/firmware.py
sungazer/models/grid.py
sungazer/models/network.py
sungazer/models/session.py
sungazer-0.2.5.dist-info/licenses/LICENSE.txt
tests/__init__.py
tests/test_CheckFWResponse.py
tests/test_DeviceDetailResponse.py
tests/test_GetCommResponse.py
tests/test_GridProfileGetResponse.py
tests/test_GridProfileRefresh.py
tests/test_StartResponse.py
tests/test_StopResponse.py
tests/test_client.py
sungazer-0.2.5.dist-info/METADATA
sungazer-0.2.5.dist-info/WHEEL
sungazer-0.2.5.dist-info/entry_points.txt
sungazer-0.2.5.dist-info/top_level.txt
sungazer-0.2.5.dist-info/RECORD
